file_renamer/__init__.py
file_renamer/__main__.py
file_renamer/__version__.py
file_renamer/gui.py
file_renamer/rename.py
file_renamer/ui_form.py
file_renamer/widget.py
file_renamer/cli/__init__.py
file_renamer/html/rc_ui.py
file_renamer/lib/case.py
file_renamer/lib/exceptions.py
file_renamer/lib/files.py
file_renamer/lib/html.py
file_renamer/themes/theme.py
file_renamer/themes/dark/dark_linux.py
file_renamer/themes/dark/dark_windows.py
file_renamer/themes/light/light_linux.py
file_renamer/themes/light/light_windows.py
io.github.flossapps.file_renamer-1.0.2.dist-info/LICENSE
io.github.flossapps.file_renamer-1.0.2.dist-info/METADATA
io.github.flossapps.file_renamer-1.0.2.dist-info/WHEEL
io.github.flossapps.file_renamer-1.0.2.dist-info/entry_points.txt
io.github.flossapps.file_renamer-1.0.2.dist-info/top_level.txt
io.github.flossapps.file_renamer-1.0.2.dist-info/RECORD
