Metadata-Version: 2.1
Name: io.github.flossapps.file-renamer
Version: 1.0.2
Summary: A desktop app for Linux and Windows for batch renaming files.
Author: Carlos
License: GNU GENERAL PUBLIC LICENSE
Project-URL: Homepage, https://github.com/flossapps/file-renamer
Project-URL: Repository, https://github.com/flossapps/file-renamer.git
Keywords: app,gui,rename,rename-files,batch-rename-files,renamer,linux-desktop,ubuntu,fedora,windows-desktop,pyside6,qt-creator
Classifier: Development Status :: 5 - Production/Stable
Classifier: License :: OSI Approved :: GNU General Public License v3 or later (GPLv3+)
Classifier: Intended Audience :: End Users/Desktop
Classifier: Topic :: Utilities
Classifier: Programming Language :: Python
Classifier: Operating System :: POSIX :: Linux
Classifier: Topic :: Desktop Environment :: Gnome
Classifier: Topic :: Desktop Environment :: K Desktop Environment (KDE)
Classifier: Operating System :: Microsoft :: Windows :: Windows 11
Requires-Python: >=3.11
License-File: LICENSE
Requires-Dist: PySide6 ~=6.8.2
Requires-Dist: PySide6-Addons ~=6.8.2
Requires-Dist: PySide6-Essentials ~=6.8.2
Requires-Dist: shiboken6 ~=6.8.2
Requires-Dist: Unidecode ~=1.3.8
